Metadata-Version: 1.0
Name: Sudoku-R
Version: 1.0
Summary: Sudoku_10X10
Home-page: UNKNOWN
Author: Raghu Kula
Author-email: raghuvarankula@gmail.com
License: UNKNOWN
Platform: UNKNOWN
